odt_at42qt1070.py
odt_at42qt1070_python-1.0.6.dist-info/LICENSE
odt_at42qt1070_python-1.0.6.dist-info/METADATA
odt_at42qt1070_python-1.0.6.dist-info/WHEEL
odt_at42qt1070_python-1.0.6.dist-info/top_level.txt
odt_at42qt1070_python-1.0.6.dist-info/RECORD
